<annotation>
	<folder>王印</folder>
	<filename>000119.jpg</filename>
	<path>C:\Users\zhanglijian\Desktop\王印\000119.jpg</path>
	<source>
		<database>Unknown</database>
	</source>
	<size>
		<width>678</width>
		<height>502</height>
		<depth>3</depth>
	</size>
	<segmented>0</segmented>
	<object>
		<name>green</name>
		<pose>Unspecified</pose>
		<truncated>0</truncated>
		<difficult>0</difficult>
		<bndbox>
			<xmin>418</xmin>
			<ymin>102</ymin>
			<xmax>450</xmax>
			<ymax>130</ymax>
		</bndbox>
	</object>
	<object>
		<name>greentime</name>
		<pose>Unspecified</pose>
		<truncated>0</truncated>
		<difficult>0</difficult>
		<bndbox>
			<xmin>494</xmin>
			<ymin>98</ymin>
			<xmax>521</xmax>
			<ymax>133</ymax>
		</bndbox>
	</object>
</annotation>
