<annotation>
	<folder>新建文件夹</folder>
	<filename>000154.jpg</filename>
	<path>C:\Users\lina\Desktop\新建文件夹\000154.jpg</path>
	<source>
		<database>Unknown</database>
	</source>
	<size>
		<width>678</width>
		<height>502</height>
		<depth>3</depth>
	</size>
	<segmented>0</segmented>
	<object>
		<name>red</name>
		<pose>Unspecified</pose>
		<truncated>0</truncated>
		<difficult>0</difficult>
		<bndbox>
			<xmin>361</xmin>
			<ymin>106</ymin>
			<xmax>391</xmax>
			<ymax>136</ymax>
		</bndbox>
	</object>
	<object>
		<name>redtime</name>
		<pose>Unspecified</pose>
		<truncated>0</truncated>
		<difficult>0</difficult>
		<bndbox>
			<xmin>487</xmin>
			<ymin>98</ymin>
			<xmax>522</xmax>
			<ymax>133</ymax>
		</bndbox>
	</object>
</annotation>
