<annotation>
	<folder>ml</folder>
	<filename>000285.jpg</filename>
	<path>C:\Users\Z_mgli\Desktop\ml\000285.jpg</path>
	<source>
		<database>Unknown</database>
	</source>
	<size>
		<width>800</width>
		<height>300</height>
		<depth>3</depth>
	</size>
	<segmented>0</segmented>
	<object>
		<name>green</name>
		<pose>Unspecified</pose>
		<truncated>0</truncated>
		<difficult>0</difficult>
		<bndbox>
			<xmin>92</xmin>
			<ymin>85</ymin>
			<xmax>135</xmax>
			<ymax>123</ymax>
		</bndbox>
	</object>
	<object>
		<name>green</name>
		<pose>Unspecified</pose>
		<truncated>0</truncated>
		<difficult>0</difficult>
		<bndbox>
			<xmin>688</xmin>
			<ymin>88</ymin>
			<xmax>729</xmax>
			<ymax>128</ymax>
		</bndbox>
	</object>
</annotation>
