<annotation>
	<folder>ml</folder>
	<filename>000292.jpg</filename>
	<path>C:\Users\Z_mgli\Desktop\ml\000292.jpg</path>
	<source>
		<database>Unknown</database>
	</source>
	<size>
		<width>1200</width>
		<height>300</height>
		<depth>3</depth>
	</size>
	<segmented>0</segmented>
	<object>
		<name>green</name>
		<pose>Unspecified</pose>
		<truncated>0</truncated>
		<difficult>0</difficult>
		<bndbox>
			<xmin>146</xmin>
			<ymin>212</ymin>
			<xmax>231</xmax>
			<ymax>279</ymax>
		</bndbox>
	</object>
	<object>
		<name>green</name>
		<pose>Unspecified</pose>
		<truncated>0</truncated>
		<difficult>0</difficult>
		<bndbox>
			<xmin>1071</xmin>
			<ymin>87</ymin>
			<xmax>1139</xmax>
			<ymax>134</ymax>
		</bndbox>
	</object>
</annotation>
