<annotation>
	<folder>sjj</folder>
	<filename>000501.jpg</filename>
	<path>C:\Users\GHB\Desktop\sjj\000501.jpg</path>
	<source>
		<database>Unknown</database>
	</source>
	<size>
		<width>600</width>
		<height>400</height>
		<depth>3</depth>
	</size>
	<segmented>0</segmented>
	<object>
		<name>greenleft</name>
		<pose>Unspecified</pose>
		<truncated>1</truncated>
		<difficult>0</difficult>
		<bndbox>
			<xmin>223</xmin>
			<ymin>355</ymin>
			<xmax>276</xmax>
			<ymax>400</ymax>
		</bndbox>
	</object>
	<object>
		<name>greenleft</name>
		<pose>Unspecified</pose>
		<truncated>0</truncated>
		<difficult>0</difficult>
		<bndbox>
			<xmin>386</xmin>
			<ymin>272</ymin>
			<xmax>402</xmax>
			<ymax>288</ymax>
		</bndbox>
	</object>
	<object>
		<name>greenstraight</name>
		<pose>Unspecified</pose>
		<truncated>0</truncated>
		<difficult>0</difficult>
		<bndbox>
			<xmin>308</xmin>
			<ymin>352</ymin>
			<xmax>353</xmax>
			<ymax>399</ymax>
		</bndbox>
	</object>
	<object>
		<name>greenstraight</name>
		<pose>Unspecified</pose>
		<truncated>0</truncated>
		<difficult>0</difficult>
		<bndbox>
			<xmin>442</xmin>
			<ymin>273</ymin>
			<xmax>459</xmax>
			<ymax>290</ymax>
		</bndbox>
	</object>
</annotation>
